mmseqspy/__init__.py
mmseqspy/cluster_utils.py
mmseqspy-0.2.0.dist-info/METADATA
mmseqspy-0.2.0.dist-info/WHEEL
mmseqspy-0.2.0.dist-info/top_level.txt
mmseqspy-0.2.0.dist-info/RECORD
